dire_rapids/__init__.py
dire_rapids/dire_cuvs.py
dire_rapids/dire_pytorch.py
dire_rapids/dire_pytorch_memory_efficient.py
dire_rapids-0.1.5.dist-info/licenses/LICENSE
docs/conf.py
dire_rapids-0.1.5.dist-info/METADATA
dire_rapids-0.1.5.dist-info/WHEEL
dire_rapids-0.1.5.dist-info/top_level.txt
dire_rapids-0.1.5.dist-info/RECORD
