Metadata-Version: 2.4
Name: dire-rapids
Version: 0.1.5
Summary: PyTorch and RAPIDS (cuVS/cuML) accelerated dimensionality reduction
Home-page: https://github.com/sashakolpakov/dire-rapids
Author: Alexander Kolpakov (UATX), Igor Rivin (Temple University)
Author-email: "Alexander Kolpakov (UATX)" <akolpakov@uaustin.org>, "Igor Rivin (Temple University)" <rivin@temple.edu>
Maintainer: Alexander Kolpakov
Maintainer-email: Alexander Kolpakov <akolpakov@uaustin.org>
License: MIT
Project-URL: Homepage, https://github.com/sashakolpakov/dire-rapids
Project-URL: Bug Reports, https://github.com/sashakolpakov/dire-rapids/issues
Project-URL: Source, https://github.com/sashakolpakov/dire-rapids
Project-URL: Documentation, https://github.com/sashakolpakov/dire-rapids#readme
Keywords: dimensionality-reduction,machine-learning,gpu,cuda,rapids,pytorch,visualization,embedding,umap,tsne
Classifier: Development Status :: 3 - Alpha
Classifier: Intended Audience :: Science/Research
Classifier: Intended Audience :: Developers
Classifier: Topic :: Scientific/Engineering :: Artificial Intelligence
Classifier: Topic :: Scientific/Engineering :: Information Analysis
Classifier: Topic :: Scientific/Engineering :: Visualization
Classifier: License :: OSI Approved :: MIT License
Classifier: Programming Language :: Python :: 3
Classifier: Programming Language :: Python :: 3.8
Classifier: Programming Language :: Python :: 3.9
Classifier: Programming Language :: Python :: 3.10
Classifier: Programming Language :: Python :: 3.11
Classifier: Operating System :: OS Independent
Classifier: Environment :: GPU :: NVIDIA CUDA
Requires-Python: >=3.8
License-File: LICENSE
Requires-Dist: numpy>=1.21.0
Requires-Dist: torch>=2.0.0
Requires-Dist: pykeops>=2.1.0
Requires-Dist: loguru>=0.6.0
Requires-Dist: tqdm>=4.62.0
Requires-Dist: scipy>=1.7.0
Requires-Dist: scikit-learn>=1.0.0
Requires-Dist: pandas>=1.3.0
Requires-Dist: plotly>=5.0.0
Requires-Dist: psutil>=5.8.0
Provides-Extra: cuda
Requires-Dist: cupy-cuda12x>=10.0.0; extra == "cuda"
Provides-Extra: rapids
Requires-Dist: cuml-cu12>=23.0.0; extra == "rapids"
Requires-Dist: cuvs-cu12>=23.0.0; extra == "rapids"
Requires-Dist: cudf-cu12>=23.0.0; extra == "rapids"
Requires-Dist: cupy-cuda12x>=10.0.0; extra == "rapids"
Provides-Extra: dev
Requires-Dist: pytest>=7.0.0; extra == "dev"
Requires-Dist: pytest-cov>=4.0.0; extra == "dev"
Requires-Dist: pytest-xdist>=3.0.0; extra == "dev"
Requires-Dist: pytest-timeout>=2.1.0; extra == "dev"
Requires-Dist: matplotlib>=3.5.0; extra == "dev"
Requires-Dist: seaborn>=0.11.0; extra == "dev"
Requires-Dist: ipython>=8.0.0; extra == "dev"
Requires-Dist: jupyter>=1.0.0; extra == "dev"
Requires-Dist: notebook>=6.4.0; extra == "dev"
Requires-Dist: black>=22.0.0; extra == "dev"
Requires-Dist: isort>=5.10.0; extra == "dev"
Requires-Dist: flake8>=4.0.0; extra == "dev"
Requires-Dist: pylint>=2.15.0; extra == "dev"
Requires-Dist: mypy>=0.950; extra == "dev"
Requires-Dist: memory_profiler>=0.60.0; extra == "dev"
Requires-Dist: line_profiler>=3.5.0; extra == "dev"
Provides-Extra: test
Requires-Dist: pytest>=7.0.0; extra == "test"
Requires-Dist: pytest-cov>=4.0.0; extra == "test"
Requires-Dist: pytest-xdist>=3.0.0; extra == "test"
Requires-Dist: pytest-timeout>=2.1.0; extra == "test"
Provides-Extra: docs
Requires-Dist: sphinx>=4.5.0; extra == "docs"
Requires-Dist: sphinx-rtd-theme>=1.0.0; extra == "docs"
Requires-Dist: nbsphinx>=0.8.0; extra == "docs"
Requires-Dist: myst-parser>=0.17.0; extra == "docs"
Dynamic: author
Dynamic: home-page
Dynamic: license-file
Dynamic: maintainer
Dynamic: requires-python
